{"name":"Inicio de sesion fallido","id":"iniciar-sesion-en-una-cuenta;inicio-de-sesion-fallido","testSteps":[{"number":1,"description":"Given El usuario se encuentra en la vista principal de la tienda","duration":5410,"startTime":"2022-03-26T21:12:34.652-05:00[America/Bogota]","result":"SUCCESS","precondition":false,"level":0,"children":[{"number":2,"description":"Cliente open landing page","duration":2907,"startTime":"2022-03-26T21:12:37.152-05:00[America/Bogota]","result":"SUCCESS","precondition":false,"level":1,"children":[{"number":3,"description":"Cliente opens the Landing page","duration":2892,"startTime":"2022-03-26T21:12:37.165-05:00[America/Bogota]","result":"SUCCESS","precondition":false,"level":2}]}]},{"number":4,"description":"And el usuario navega al modulo de Sign In","duration":1786,"startTime":"2022-03-26T21:12:40.063-05:00[America/Bogota]","result":"SUCCESS","precondition":false,"level":0,"children":[{"number":5,"description":"Cliente go to sign in page","duration":1781,"startTime":"2022-03-26T21:12:40.067-05:00[America/Bogota]","result":"SUCCESS","precondition":false,"level":1,"children":[{"number":6,"description":"Cliente clicks on Sign in button","duration":1703,"startTime":"2022-03-26T21:12:40.142-05:00[America/Bogota]","result":"SUCCESS","precondition":false,"level":2}]}]},{"number":7,"description":"When el usuario ingresa el email registrado con una contrasenia incorrecta","duration":2224,"startTime":"2022-03-26T21:12:41.849-05:00[America/Bogota]","result":"SUCCESS","precondition":false,"level":0,"children":[{"number":8,"description":"Cliente log in","duration":2208,"startTime":"2022-03-26T21:12:41.855-05:00[America/Bogota]","result":"SUCCESS","precondition":false,"level":1,"children":[{"number":9,"description":"Cliente enters \u0027oKxZmNXZjc@gmail.com\u0027 into Email input field","duration":326,"startTime":"2022-03-26T21:12:41.935-05:00[America/Bogota]","result":"SUCCESS","precondition":false,"level":2},{"number":10,"description":"Cliente enters \u0027123451\u0027 into Password input field","duration":406,"startTime":"2022-03-26T21:12:42.321-05:00[America/Bogota]","result":"SUCCESS","precondition":false,"level":2},{"number":11,"description":"Cliente clicks on Submit login button","duration":1271,"startTime":"2022-03-26T21:12:42.792-05:00[America/Bogota]","result":"SUCCESS","precondition":false,"level":2}]}]},{"number":12,"description":"Then el sistema mostrara un mensaje de autenticacion fallida","duration":85,"startTime":"2022-03-26T21:12:44.075-05:00[America/Bogota]","result":"SUCCESS","precondition":false,"level":0,"children":[{"number":13,"description":"Then wrong password error should be (true)","duration":84,"startTime":"2022-03-26T21:12:44.076-05:00[America/Bogota]","result":"SUCCESS","precondition":false,"level":1}]}],"userStory":{"id":"iniciar-sesion-en-una-cuenta","storyName":"Iniciar sesion en una cuenta","path":"file:///D:/SofkaU/Introduccion%20a%20la%20automatizacion/Intellij/retoAutomatizacionSerenityBDDScreenplayWebUI/src/test/resources/features/signin/signIn.feature","narrative":"  yo como usuario\n  quiero poder iniciar sesion en mi cuenta\n  para poder administrar mis datos en la tienda","type":"feature"},"featureTag":{"name":"Signin/Iniciar sesion en una cuenta","type":"feature","displayName":"Signin/Iniciar sesion en una cuenta"},"title":"Inicio de sesion fallido","backgroundTitle":"","backgroundDescription":"","tags":[{"name":"Signin","type":"capability","displayName":"Signin"},{"name":"Signin/Iniciar sesion en una cuenta","type":"feature","displayName":"Iniciar sesion en una cuenta"}],"startTime":"2022-03-26T21:12:34.652-05:00[America/Bogota]","duration":9508,"projectKey":"","sessionId":"4b437a21313f6b2708182a5de14894cb","driver":"chrome","isManualTestingUpToDate":false,"manual":false,"testSource":"Cucumber","actors":[{"name":"Cliente","can":["browse the web"]}],"result":"SUCCESS"}